erspy/__init__.py
erspy/asps.py
erspy-0.2.dist-info/LICENSE.txt
erspy-0.2.dist-info/METADATA
erspy-0.2.dist-info/WHEEL
erspy-0.2.dist-info/top_level.txt
erspy-0.2.dist-info/RECORD
